ChangeLog
LICENSE.txt
MANIFEST.in
README.rst
setup.py
v20/__init__.py
v20/account.py
v20/base_entity.py
v20/errors.py
v20/instrument.py
v20/order.py
v20/position.py
v20/pricing.py
v20/pricing_common.py
v20/primitives.py
v20/request.py
v20/response.py
v20/site.py
v20/spec_properties.py
v20/trade.py
v20/transaction.py
v20/user.py
v20.egg-info/PKG-INFO
v20.egg-info/SOURCES.txt
v20.egg-info/dependency_links.txt
v20.egg-info/requires.txt
v20.egg-info/top_level.txt
v20.egg-info/zip-safe