Metadata-Version: 1.1
Name: v20
Version: 3.0.25.0
Summary: OANDA v20 bindings for Python
Home-page: https://github.com/oanda/v20-python
Author: OANDA Corporation
Author-email: api@oanda.com
License: MIT
Platform: any
Classifier: Development Status :: 5 - Production/Stable
Classifier: Environment :: Console
Classifier: Intended Audience :: Developers
Classifier: License :: Other/Proprietary License
Classifier: Natural Language :: English
Classifier: Operating System :: OS Independent
Classifier: Programming Language :: Python :: 2.7
Classifier: Programming Language :: Python :: 3.5
Classifier: Topic :: Software Development
Classifier: Topic :: Software Development :: Libraries
Classifier: Topic :: Utilities
